{
  "ticker": "ETH",
  "fecha": "2026-04-12T20:47:57.923227",
  "es_cripto": true,
  "veredicto": "PRECAUCION",
  "score": 2,
  "precio": {
    "precio_actual": 2198.3857,
    "cambio_24h": -3.81,
    "cambio_7d": 4.24,
    "cambio_30d": 7.08,
    "high_52w": 4831.3486,
    "low_52w": 1821.6831,
    "vol_hoy": 15288977408,
    "vol_20d_avg": 16052084903,
    "vol_relativo": 0.95,
    "cambio_ytd": -26.73,
    "sma_20": 2117.9674,
    "sma_50": 2079.9097,
    "sma_200": 2917.9937,
    "soporte": 1852.9695,
    "resistencia": 2351.176,
    "tendencia_sma": "MIXTA",
    "rsi": 66.15,
    "macd_line": 35.5712,
    "macd_signal": 18.1721,
    "macd_bullish": true
  },
  "info": {
    "market_cap": 265325477888.0,
    "circulating": 120691056.0
  },
  "fundamentales": {},
  "fair_value": {},
  "dcf": {},
  "escenarios": {},
  "moat": {},
  "riesgos": [],
  "eventos": {},
  "sector_contexto": {},
  "sentimiento": {
    "fuente": "Análisis cuantitativo (precio + técnico + analistas)",
    "score": 1,
    "max": 10,
    "label": "NEUTRAL",
    "señales": [
      {
        "factor": "RSI Alto",
        "valor": "66",
        "señal": "NEUTRAL",
        "peso": "-1",
        "desc": "Momentum positivo pero acercándose a sobrecompra"
      },
      {
        "factor": "Tendencia SMA",
        "valor": "MIXTA",
        "señal": "NEUTRAL",
        "peso": "0",
        "desc": "Señales técnicas contradictorias"
      },
      {
        "factor": "MACD",
        "valor": "Alcista",
        "señal": "BULLISH",
        "peso": "+1",
        "desc": "Cruce MACD alcista — momentum de corto plazo positivo"
      },
      {
        "factor": "Posición 52s",
        "valor": "13%",
        "señal": "BULLISH",
        "peso": "+1",
        "desc": "Cerca del mínimo anual — posible valor en zona baja histórica"
      }
    ]
  },
  "noticias_ticker": [
    {
      "title": "Bit Digital CEO discusses Ethereum strategy, AI expansion - ICYMI",
      "url": "https://www.proactiveinvestors.com/companies/news/1090378/bit-digital-ceo-discusses-ethereum-strategy-ai-expansion-icymi-1090378.html",
      "source": "Proactive",
      "date": "2026-04-11",
      "sentiment": "bullish"
    },
    {
      "title": "$1.5 Billion Ethereum Treasury Ether Machine Deal Collapses",
      "url": "https://beincrypto.com/ether-machine-dynamix-spac-deal-terminated/",
      "source": "BeInCrypto",
      "date": "2026-04-11",
      "sentiment": "bullish"
    },
    {
      "title": "Alchemy launches $20 million fund for Solana builders",
      "url": "https://www.thestreet.com/crypto/markets/alchemy-launches-20-million-fund-for-solana-builders",
      "source": "TheStreet",
      "date": "2026-04-10",
      "sentiment": "bullish"
    },
    {
      "title": "Bitcoin, Solana, XRP, Dogecoin Show Signs Of Bottoming: Watch This 'Golden Zone'",
      "url": "https://finance.yahoo.com/markets/crypto/articles/bitcoin-solana-xrp-dogecoin-show-104613664.html",
      "source": "Benzinga",
      "date": "2026-04-11",
      "sentiment": "bearish"
    },
    {
      "title": "US-Iran Talks Breakdown, Bitcoin looses Weekend Gains",
      "url": "https://beincrypto.com/bitcoin-price-drops-us-iran-talks-fail/",
      "source": "BeInCrypto",
      "date": "2026-04-12",
      "sentiment": "bearish"
    }
  ],
  "noticias_macro": [
    {
      "title": "Trump announces blockade of Strait of Hormuz as Vance leaves Pakistan talks with no deal. How financial markets are reacting.",
      "url": "https://www.marketwatch.com/story/vance-leaves-pakistan-talks-with-no-deal-how-financial-markets-are-reacting-ef6916b3?mod=mw_rss_topstories",
      "source": "MarketWatch",
      "sentiment": "bullish"
    },
    {
      "title": "Stock-market futures drop, oil surges back above $100 after failed talks between U.S. and Iran over the weekend",
      "url": "https://www.marketwatch.com/story/stock-market-futures-drop-oil-surges-above-100-after-failed-talks-between-u-s-and-iran-over-the-weekend-7b741637?mod=mw_rss_topstories",
      "source": "MarketWatch",
      "sentiment": "bullish"
    },
    {
      "title": "Trump says he’s closing the Strait of Hormuz. Has he been reading MarketWatch?",
      "url": "https://www.marketwatch.com/story/trump-says-hes-closing-the-strait-of-hormuz-has-he-been-reading-marketwatch-e059dd07?mod=mw_rss_topstories",
      "source": "MarketWatch",
      "sentiment": "neutral"
    },
    {
      "title": "‘I feel pressured’: My husband has early Alzheimer’s and wants to visit Europe, but I’m terrified of flying. What should I do?",
      "url": "https://www.marketwatch.com/story/i-feel-pressured-my-husband-has-early-alzheimers-and-wants-to-visit-europe-but-im-terrified-of-flying-what-should-i-do-c5cc01bf?mod=mw_rss_topstories",
      "source": "MarketWatch",
      "sentiment": "neutral"
    }
  ]
}